[
    {
        "round": 1,
        "a_contribution": 8,
        "a_gain": 11.200000000000001,
        "a_total_points_after_round": 11.200000000000001,
        "b_contribution": 5,
        "b_gain": 14.200000000000001,
        "b_total_points_after_round": 14.200000000000001,
        "c_contribution": 5,
        "c_gain": 14.200000000000001,
        "c_total_points_after_round": 14.200000000000001,
        "d_contribution": 5,
        "d_gain": 14.200000000000001,
        "d_total_points_after_round": 14.200000000000001,
        "total_contribution_round": 23
    },
    {
        "round": 2,
        "a_contribution": 7,
        "a_gain": 13.0,
        "a_total_points_after_round": 24.200000000000003,
        "b_contribution": 6,
        "b_gain": 14.0,
        "b_total_points_after_round": 28.200000000000003,
        "c_contribution": 5,
        "c_gain": 15.0,
        "c_total_points_after_round": 29.200000000000003,
        "d_contribution": 7,
        "d_gain": 13.0,
        "d_total_points_after_round": 27.200000000000003,
        "total_contribution_round": 25
    },
    {
        "round": 3,
        "a_contribution": 7,
        "a_gain": 13.4,
        "a_total_points_after_round": 37.6,
        "b_contribution": 7,
        "b_gain": 13.4,
        "b_total_points_after_round": 41.6,
        "c_contribution": 5,
        "c_gain": 15.4,
        "c_total_points_after_round": 44.6,
        "d_contribution": 7,
        "d_gain": 13.4,
        "d_total_points_after_round": 40.6,
        "total_contribution_round": 26
    },
    {
        "round": 4,
        "a_contribution": 7,
        "a_gain": 13.4,
        "a_total_points_after_round": 51.0,
        "b_contribution": 8,
        "b_gain": 12.4,
        "b_total_points_after_round": 54.0,
        "c_contribution": 5,
        "c_gain": 15.4,
        "c_total_points_after_round": 60.0,
        "d_contribution": 6,
        "d_gain": 14.4,
        "d_total_points_after_round": 55.0,
        "total_contribution_round": 26
    },
    {
        "round": 5,
        "a_contribution": 7,
        "a_gain": 13.8,
        "a_total_points_after_round": 64.8,
        "b_contribution": 8,
        "b_gain": 12.8,
        "b_total_points_after_round": 66.8,
        "c_contribution": 5,
        "c_gain": 15.8,
        "c_total_points_after_round": 75.8,
        "d_contribution": 7,
        "d_gain": 13.8,
        "d_total_points_after_round": 68.8,
        "total_contribution_round": 27
    },
    {
        "round": 6,
        "a_contribution": 7,
        "a_gain": 14.200000000000001,
        "a_total_points_after_round": 79.0,
        "b_contribution": 9,
        "b_gain": 12.200000000000001,
        "b_total_points_after_round": 79.0,
        "c_contribution": 5,
        "c_gain": 16.200000000000003,
        "c_total_points_after_round": 92.0,
        "d_contribution": 7,
        "d_gain": 14.200000000000001,
        "d_total_points_after_round": 83.0,
        "total_contribution_round": 28
    },
    {
        "round": 7,
        "a_contribution": 7,
        "a_gain": 14.200000000000001,
        "a_total_points_after_round": 93.2,
        "b_contribution": 9,
        "b_gain": 12.200000000000001,
        "b_total_points_after_round": 91.2,
        "c_contribution": 5,
        "c_gain": 16.200000000000003,
        "c_total_points_after_round": 108.2,
        "d_contribution": 7,
        "d_gain": 14.200000000000001,
        "d_total_points_after_round": 97.2,
        "total_contribution_round": 28
    },
    {
        "round": 8,
        "a_contribution": 7,
        "a_gain": 14.600000000000001,
        "a_total_points_after_round": 107.80000000000001,
        "b_contribution": 10,
        "b_gain": 11.600000000000001,
        "b_total_points_after_round": 102.80000000000001,
        "c_contribution": 5,
        "c_gain": 16.6,
        "c_total_points_after_round": 124.80000000000001,
        "d_contribution": 7,
        "d_gain": 14.600000000000001,
        "d_total_points_after_round": 111.80000000000001,
        "total_contribution_round": 29
    },
    {
        "round": 9,
        "a_contribution": 7,
        "a_gain": 14.600000000000001,
        "a_total_points_after_round": 122.4,
        "b_contribution": 10,
        "b_gain": 11.600000000000001,
        "b_total_points_after_round": 114.4,
        "c_contribution": 5,
        "c_gain": 16.6,
        "c_total_points_after_round": 141.4,
        "d_contribution": 7,
        "d_gain": 14.600000000000001,
        "d_total_points_after_round": 126.4,
        "total_contribution_round": 29
    },
    {
        "round": 10,
        "a_contribution": 7,
        "a_gain": 14.600000000000001,
        "a_total_points_after_round": 137.0,
        "b_contribution": 10,
        "b_gain": 11.600000000000001,
        "b_total_points_after_round": 126.0,
        "c_contribution": 5,
        "c_gain": 16.6,
        "c_total_points_after_round": 158.0,
        "d_contribution": 7,
        "d_gain": 14.600000000000001,
        "d_total_points_after_round": 141.0,
        "total_contribution_round": 29
    },
    {
        "round": 11,
        "a_contribution": 7,
        "a_gain": 14.200000000000001,
        "a_total_points_after_round": 151.2,
        "b_contribution": 9,
        "b_gain": 12.200000000000001,
        "b_total_points_after_round": 138.2,
        "c_contribution": 5,
        "c_gain": 16.200000000000003,
        "c_total_points_after_round": 174.2,
        "d_contribution": 7,
        "d_gain": 14.200000000000001,
        "d_total_points_after_round": 155.2,
        "total_contribution_round": 28
    },
    {
        "round": 12,
        "a_contribution": 7,
        "a_gain": 13.8,
        "a_total_points_after_round": 165.0,
        "b_contribution": 8,
        "b_gain": 12.8,
        "b_total_points_after_round": 151.0,
        "c_contribution": 5,
        "c_gain": 15.8,
        "c_total_points_after_round": 190.0,
        "d_contribution": 7,
        "d_gain": 13.8,
        "d_total_points_after_round": 169.0,
        "total_contribution_round": 27
    },
    {
        "round": 13,
        "a_contribution": 7,
        "a_gain": 13.4,
        "a_total_points_after_round": 178.4,
        "b_contribution": 7,
        "b_gain": 13.4,
        "b_total_points_after_round": 164.4,
        "c_contribution": 5,
        "c_gain": 15.4,
        "c_total_points_after_round": 205.4,
        "d_contribution": 7,
        "d_gain": 13.4,
        "d_total_points_after_round": 182.4,
        "total_contribution_round": 26
    },
    {
        "round": 14,
        "a_contribution": 7,
        "a_gain": 13.0,
        "a_total_points_after_round": 191.4,
        "b_contribution": 6,
        "b_gain": 14.0,
        "b_total_points_after_round": 178.4,
        "c_contribution": 5,
        "c_gain": 15.0,
        "c_total_points_after_round": 220.4,
        "d_contribution": 7,
        "d_gain": 13.0,
        "d_total_points_after_round": 195.4,
        "total_contribution_round": 25
    },
    {
        "round": 15,
        "a_contribution": 7,
        "a_gain": 12.600000000000001,
        "a_total_points_after_round": 204.0,
        "b_contribution": 5,
        "b_gain": 14.600000000000001,
        "b_total_points_after_round": 193.0,
        "c_contribution": 5,
        "c_gain": 14.600000000000001,
        "c_total_points_after_round": 235.0,
        "d_contribution": 7,
        "d_gain": 12.600000000000001,
        "d_total_points_after_round": 208.0,
        "total_contribution_round": 24
    },
    {
        "round": 16,
        "a_contribution": 6,
        "a_gain": 13.200000000000001,
        "a_total_points_after_round": 217.2,
        "b_contribution": 5,
        "b_gain": 14.200000000000001,
        "b_total_points_after_round": 207.2,
        "c_contribution": 5,
        "c_gain": 14.200000000000001,
        "c_total_points_after_round": 249.2,
        "d_contribution": 7,
        "d_gain": 12.200000000000001,
        "d_total_points_after_round": 220.2,
        "total_contribution_round": 23
    },
    {
        "round": 17,
        "a_contribution": 6,
        "a_gain": 12.4,
        "a_total_points_after_round": 229.6,
        "b_contribution": 4,
        "b_gain": 14.4,
        "b_total_points_after_round": 221.6,
        "c_contribution": 5,
        "c_gain": 13.4,
        "c_total_points_after_round": 262.59999999999997,
        "d_contribution": 6,
        "d_gain": 12.4,
        "d_total_points_after_round": 232.6,
        "total_contribution_round": 21
    },
    {
        "round": 18,
        "a_contribution": 6,
        "a_gain": 11.2,
        "a_total_points_after_round": 240.79999999999998,
        "b_contribution": 3,
        "b_gain": 14.2,
        "b_total_points_after_round": 235.79999999999998,
        "c_contribution": 4,
        "c_gain": 13.2,
        "c_total_points_after_round": 275.79999999999995,
        "d_contribution": 5,
        "d_gain": 12.2,
        "d_total_points_after_round": 244.79999999999998,
        "total_contribution_round": 18
    },
    {
        "round": 19,
        "a_contribution": 5,
        "a_gain": 11.0,
        "a_total_points_after_round": 251.79999999999998,
        "b_contribution": 2,
        "b_gain": 14.0,
        "b_total_points_after_round": 249.79999999999998,
        "c_contribution": 3,
        "c_gain": 13.0,
        "c_total_points_after_round": 288.79999999999995,
        "d_contribution": 5,
        "d_gain": 11.0,
        "d_total_points_after_round": 255.79999999999998,
        "total_contribution_round": 15
    },
    {
        "round": 20,
        "a_contribution": 0,
        "a_gain": 10.0,
        "a_total_points_after_round": 261.79999999999995,
        "b_contribution": 0,
        "b_gain": 10.0,
        "b_total_points_after_round": 259.79999999999995,
        "c_contribution": 0,
        "c_gain": 10.0,
        "c_total_points_after_round": 298.79999999999995,
        "d_contribution": 0,
        "d_gain": 10.0,
        "d_total_points_after_round": 265.79999999999995,
        "total_contribution_round": 0
    }
]