[
    {
        "round": 1,
        "a_contribution": 5,
        "a_gain": 12.2,
        "a_total_points_after_round": 12.2,
        "b_contribution": 5,
        "b_gain": 12.2,
        "b_total_points_after_round": 12.2,
        "c_contribution": 5,
        "c_gain": 12.2,
        "c_total_points_after_round": 12.2,
        "d_contribution": 3,
        "d_gain": 14.2,
        "d_total_points_after_round": 14.2,
        "total_contribution_round": 18
    },
    {
        "round": 2,
        "a_contribution": 6,
        "a_gain": 13.200000000000001,
        "a_total_points_after_round": 25.4,
        "b_contribution": 6,
        "b_gain": 13.200000000000001,
        "b_total_points_after_round": 25.4,
        "c_contribution": 6,
        "c_gain": 13.200000000000001,
        "c_total_points_after_round": 25.4,
        "d_contribution": 5,
        "d_gain": 14.200000000000001,
        "d_total_points_after_round": 28.4,
        "total_contribution_round": 23
    },
    {
        "round": 3,
        "a_contribution": 7,
        "a_gain": 13.0,
        "a_total_points_after_round": 38.4,
        "b_contribution": 4,
        "b_gain": 16.0,
        "b_total_points_after_round": 41.4,
        "c_contribution": 7,
        "c_gain": 13.0,
        "c_total_points_after_round": 38.4,
        "d_contribution": 7,
        "d_gain": 13.0,
        "d_total_points_after_round": 41.4,
        "total_contribution_round": 25
    },
    {
        "round": 4,
        "a_contribution": 5,
        "a_gain": 14.200000000000001,
        "a_total_points_after_round": 52.6,
        "b_contribution": 3,
        "b_gain": 16.200000000000003,
        "b_total_points_after_round": 57.6,
        "c_contribution": 7,
        "c_gain": 12.200000000000001,
        "c_total_points_after_round": 50.6,
        "d_contribution": 8,
        "d_gain": 11.200000000000001,
        "d_total_points_after_round": 52.6,
        "total_contribution_round": 23
    },
    {
        "round": 5,
        "a_contribution": 6,
        "a_gain": 11.600000000000001,
        "a_total_points_after_round": 64.2,
        "b_contribution": 4,
        "b_gain": 13.600000000000001,
        "b_total_points_after_round": 71.2,
        "c_contribution": 5,
        "c_gain": 12.600000000000001,
        "c_total_points_after_round": 63.2,
        "d_contribution": 4,
        "d_gain": 13.600000000000001,
        "d_total_points_after_round": 66.2,
        "total_contribution_round": 19
    },
    {
        "round": 6,
        "a_contribution": 4,
        "a_gain": 13.600000000000001,
        "a_total_points_after_round": 77.80000000000001,
        "b_contribution": 5,
        "b_gain": 12.600000000000001,
        "b_total_points_after_round": 83.80000000000001,
        "c_contribution": 6,
        "c_gain": 11.600000000000001,
        "c_total_points_after_round": 74.80000000000001,
        "d_contribution": 4,
        "d_gain": 13.600000000000001,
        "d_total_points_after_round": 79.80000000000001,
        "total_contribution_round": 19
    },
    {
        "round": 7,
        "a_contribution": 5,
        "a_gain": 11.8,
        "a_total_points_after_round": 89.60000000000001,
        "b_contribution": 4,
        "b_gain": 12.8,
        "b_total_points_after_round": 96.60000000000001,
        "c_contribution": 4,
        "c_gain": 12.8,
        "c_total_points_after_round": 87.60000000000001,
        "d_contribution": 4,
        "d_gain": 12.8,
        "d_total_points_after_round": 92.60000000000001,
        "total_contribution_round": 17
    },
    {
        "round": 8,
        "a_contribution": 3,
        "a_gain": 12.600000000000001,
        "a_total_points_after_round": 102.20000000000002,
        "b_contribution": 3,
        "b_gain": 12.600000000000001,
        "b_total_points_after_round": 109.20000000000002,
        "c_contribution": 5,
        "c_gain": 10.600000000000001,
        "c_total_points_after_round": 98.20000000000002,
        "d_contribution": 3,
        "d_gain": 12.600000000000001,
        "d_total_points_after_round": 105.20000000000002,
        "total_contribution_round": 14
    },
    {
        "round": 9,
        "a_contribution": 4,
        "a_gain": 10.8,
        "a_total_points_after_round": 113.00000000000001,
        "b_contribution": 2,
        "b_gain": 12.8,
        "b_total_points_after_round": 122.00000000000001,
        "c_contribution": 4,
        "c_gain": 10.8,
        "c_total_points_after_round": 109.00000000000001,
        "d_contribution": 2,
        "d_gain": 12.8,
        "d_total_points_after_round": 118.00000000000001,
        "total_contribution_round": 12
    },
    {
        "round": 10,
        "a_contribution": 2,
        "a_gain": 12.8,
        "a_total_points_after_round": 125.80000000000001,
        "b_contribution": 4,
        "b_gain": 10.8,
        "b_total_points_after_round": 132.8,
        "c_contribution": 3,
        "c_gain": 11.8,
        "c_total_points_after_round": 120.80000000000001,
        "d_contribution": 3,
        "d_gain": 11.8,
        "d_total_points_after_round": 129.8,
        "total_contribution_round": 12
    },
    {
        "round": 11,
        "a_contribution": 3,
        "a_gain": 13.0,
        "a_total_points_after_round": 138.8,
        "b_contribution": 5,
        "b_gain": 11.0,
        "b_total_points_after_round": 143.8,
        "c_contribution": 4,
        "c_gain": 12.0,
        "c_total_points_after_round": 132.8,
        "d_contribution": 3,
        "d_gain": 13.0,
        "d_total_points_after_round": 142.8,
        "total_contribution_round": 15
    },
    {
        "round": 12,
        "a_contribution": 4,
        "a_gain": 12.0,
        "a_total_points_after_round": 150.8,
        "b_contribution": 3,
        "b_gain": 13.0,
        "b_total_points_after_round": 156.8,
        "c_contribution": 4,
        "c_gain": 12.0,
        "c_total_points_after_round": 144.8,
        "d_contribution": 4,
        "d_gain": 12.0,
        "d_total_points_after_round": 154.8,
        "total_contribution_round": 15
    },
    {
        "round": 13,
        "a_contribution": 3,
        "a_gain": 13.0,
        "a_total_points_after_round": 163.8,
        "b_contribution": 4,
        "b_gain": 12.0,
        "b_total_points_after_round": 168.8,
        "c_contribution": 3,
        "c_gain": 13.0,
        "c_total_points_after_round": 157.8,
        "d_contribution": 5,
        "d_gain": 11.0,
        "d_total_points_after_round": 165.8,
        "total_contribution_round": 15
    },
    {
        "round": 14,
        "a_contribution": 2,
        "a_gain": 13.600000000000001,
        "a_total_points_after_round": 177.4,
        "b_contribution": 5,
        "b_gain": 10.600000000000001,
        "b_total_points_after_round": 179.4,
        "c_contribution": 3,
        "c_gain": 12.600000000000001,
        "c_total_points_after_round": 170.4,
        "d_contribution": 4,
        "d_gain": 11.600000000000001,
        "d_total_points_after_round": 177.4,
        "total_contribution_round": 14
    },
    {
        "round": 15,
        "a_contribution": 3,
        "a_gain": 11.8,
        "a_total_points_after_round": 189.20000000000002,
        "b_contribution": 4,
        "b_gain": 10.8,
        "b_total_points_after_round": 190.20000000000002,
        "c_contribution": 2,
        "c_gain": 12.8,
        "c_total_points_after_round": 183.20000000000002,
        "d_contribution": 3,
        "d_gain": 11.8,
        "d_total_points_after_round": 189.20000000000002,
        "total_contribution_round": 12
    },
    {
        "round": 16,
        "a_contribution": 2,
        "a_gain": 11.6,
        "a_total_points_after_round": 200.8,
        "b_contribution": 3,
        "b_gain": 10.6,
        "b_total_points_after_round": 200.8,
        "c_contribution": 2,
        "c_gain": 11.6,
        "c_total_points_after_round": 194.8,
        "d_contribution": 2,
        "d_gain": 11.6,
        "d_total_points_after_round": 200.8,
        "total_contribution_round": 9
    },
    {
        "round": 17,
        "a_contribution": 3,
        "a_gain": 11.0,
        "a_total_points_after_round": 211.8,
        "b_contribution": 2,
        "b_gain": 12.0,
        "b_total_points_after_round": 212.8,
        "c_contribution": 1,
        "c_gain": 13.0,
        "c_total_points_after_round": 207.8,
        "d_contribution": 4,
        "d_gain": 10.0,
        "d_total_points_after_round": 210.8,
        "total_contribution_round": 10
    },
    {
        "round": 18,
        "a_contribution": 2,
        "a_gain": 11.2,
        "a_total_points_after_round": 223.0,
        "b_contribution": 0,
        "b_gain": 13.2,
        "b_total_points_after_round": 226.0,
        "c_contribution": 2,
        "c_gain": 11.2,
        "c_total_points_after_round": 219.0,
        "d_contribution": 4,
        "d_gain": 9.2,
        "d_total_points_after_round": 220.0,
        "total_contribution_round": 8
    },
    {
        "round": 19,
        "a_contribution": 3,
        "a_gain": 9.8,
        "a_total_points_after_round": 232.8,
        "b_contribution": 0,
        "b_gain": 12.8,
        "b_total_points_after_round": 238.8,
        "c_contribution": 1,
        "c_gain": 11.8,
        "c_total_points_after_round": 230.8,
        "d_contribution": 3,
        "d_gain": 9.8,
        "d_total_points_after_round": 229.8,
        "total_contribution_round": 7
    },
    {
        "round": 20,
        "a_contribution": 2,
        "a_gain": 10.0,
        "a_total_points_after_round": 242.8,
        "b_contribution": 0,
        "b_gain": 12.0,
        "b_total_points_after_round": 250.8,
        "c_contribution": 1,
        "c_gain": 11.0,
        "c_total_points_after_round": 241.8,
        "d_contribution": 2,
        "d_gain": 10.0,
        "d_total_points_after_round": 239.8,
        "total_contribution_round": 5
    }
]