[
    {
        "round": 1,
        "a_contribution": 5,
        "a_gain": 15.4,
        "a_total_points_after_round": 15.4,
        "b_contribution": 8,
        "b_gain": 12.4,
        "b_total_points_after_round": 12.4,
        "c_contribution": 8,
        "c_gain": 12.4,
        "c_total_points_after_round": 12.4,
        "d_contribution": 5,
        "d_gain": 15.4,
        "d_total_points_after_round": 15.4,
        "total_contribution_round": 26
    },
    {
        "round": 2,
        "a_contribution": 6,
        "a_gain": 15.200000000000001,
        "a_total_points_after_round": 30.6,
        "b_contribution": 8,
        "b_gain": 13.200000000000001,
        "b_total_points_after_round": 25.6,
        "c_contribution": 8,
        "c_gain": 13.200000000000001,
        "c_total_points_after_round": 25.6,
        "d_contribution": 6,
        "d_gain": 15.200000000000001,
        "d_total_points_after_round": 30.6,
        "total_contribution_round": 28
    },
    {
        "round": 3,
        "a_contribution": 6,
        "a_gain": 15.600000000000001,
        "a_total_points_after_round": 46.2,
        "b_contribution": 8,
        "b_gain": 13.600000000000001,
        "b_total_points_after_round": 39.2,
        "c_contribution": 8,
        "c_gain": 13.600000000000001,
        "c_total_points_after_round": 39.2,
        "d_contribution": 7,
        "d_gain": 14.600000000000001,
        "d_total_points_after_round": 45.2,
        "total_contribution_round": 29
    },
    {
        "round": 4,
        "a_contribution": 7,
        "a_gain": 14.600000000000001,
        "a_total_points_after_round": 60.800000000000004,
        "b_contribution": 8,
        "b_gain": 13.600000000000001,
        "b_total_points_after_round": 52.800000000000004,
        "c_contribution": 8,
        "c_gain": 13.600000000000001,
        "c_total_points_after_round": 52.800000000000004,
        "d_contribution": 6,
        "d_gain": 15.600000000000001,
        "d_total_points_after_round": 60.800000000000004,
        "total_contribution_round": 29
    },
    {
        "round": 5,
        "a_contribution": 7,
        "a_gain": 15.0,
        "a_total_points_after_round": 75.80000000000001,
        "b_contribution": 8,
        "b_gain": 14.0,
        "b_total_points_after_round": 66.80000000000001,
        "c_contribution": 8,
        "c_gain": 14.0,
        "c_total_points_after_round": 66.80000000000001,
        "d_contribution": 7,
        "d_gain": 15.0,
        "d_total_points_after_round": 75.80000000000001,
        "total_contribution_round": 30
    },
    {
        "round": 6,
        "a_contribution": 7,
        "a_gain": 15.0,
        "a_total_points_after_round": 90.80000000000001,
        "b_contribution": 8,
        "b_gain": 14.0,
        "b_total_points_after_round": 80.80000000000001,
        "c_contribution": 8,
        "c_gain": 14.0,
        "c_total_points_after_round": 80.80000000000001,
        "d_contribution": 7,
        "d_gain": 15.0,
        "d_total_points_after_round": 90.80000000000001,
        "total_contribution_round": 30
    },
    {
        "round": 7,
        "a_contribution": 7,
        "a_gain": 15.0,
        "a_total_points_after_round": 105.80000000000001,
        "b_contribution": 8,
        "b_gain": 14.0,
        "b_total_points_after_round": 94.80000000000001,
        "c_contribution": 8,
        "c_gain": 14.0,
        "c_total_points_after_round": 94.80000000000001,
        "d_contribution": 7,
        "d_gain": 15.0,
        "d_total_points_after_round": 105.80000000000001,
        "total_contribution_round": 30
    },
    {
        "round": 8,
        "a_contribution": 7,
        "a_gain": 15.4,
        "a_total_points_after_round": 121.20000000000002,
        "b_contribution": 8,
        "b_gain": 14.4,
        "b_total_points_after_round": 109.20000000000002,
        "c_contribution": 8,
        "c_gain": 14.4,
        "c_total_points_after_round": 109.20000000000002,
        "d_contribution": 8,
        "d_gain": 14.4,
        "d_total_points_after_round": 120.20000000000002,
        "total_contribution_round": 31
    },
    {
        "round": 9,
        "a_contribution": 7,
        "a_gain": 15.4,
        "a_total_points_after_round": 136.60000000000002,
        "b_contribution": 8,
        "b_gain": 14.4,
        "b_total_points_after_round": 123.60000000000002,
        "c_contribution": 8,
        "c_gain": 14.4,
        "c_total_points_after_round": 123.60000000000002,
        "d_contribution": 8,
        "d_gain": 14.4,
        "d_total_points_after_round": 134.60000000000002,
        "total_contribution_round": 31
    },
    {
        "round": 10,
        "a_contribution": 7,
        "a_gain": 15.0,
        "a_total_points_after_round": 151.60000000000002,
        "b_contribution": 8,
        "b_gain": 14.0,
        "b_total_points_after_round": 137.60000000000002,
        "c_contribution": 8,
        "c_gain": 14.0,
        "c_total_points_after_round": 137.60000000000002,
        "d_contribution": 7,
        "d_gain": 15.0,
        "d_total_points_after_round": 149.60000000000002,
        "total_contribution_round": 30
    },
    {
        "round": 11,
        "a_contribution": 7,
        "a_gain": 15.0,
        "a_total_points_after_round": 166.60000000000002,
        "b_contribution": 8,
        "b_gain": 14.0,
        "b_total_points_after_round": 151.60000000000002,
        "c_contribution": 8,
        "c_gain": 14.0,
        "c_total_points_after_round": 151.60000000000002,
        "d_contribution": 7,
        "d_gain": 15.0,
        "d_total_points_after_round": 164.60000000000002,
        "total_contribution_round": 30
    },
    {
        "round": 12,
        "a_contribution": 7,
        "a_gain": 15.0,
        "a_total_points_after_round": 181.60000000000002,
        "b_contribution": 8,
        "b_gain": 14.0,
        "b_total_points_after_round": 165.60000000000002,
        "c_contribution": 8,
        "c_gain": 14.0,
        "c_total_points_after_round": 165.60000000000002,
        "d_contribution": 7,
        "d_gain": 15.0,
        "d_total_points_after_round": 179.60000000000002,
        "total_contribution_round": 30
    },
    {
        "round": 13,
        "a_contribution": 7,
        "a_gain": 15.0,
        "a_total_points_after_round": 196.60000000000002,
        "b_contribution": 8,
        "b_gain": 14.0,
        "b_total_points_after_round": 179.60000000000002,
        "c_contribution": 8,
        "c_gain": 14.0,
        "c_total_points_after_round": 179.60000000000002,
        "d_contribution": 7,
        "d_gain": 15.0,
        "d_total_points_after_round": 194.60000000000002,
        "total_contribution_round": 30
    },
    {
        "round": 14,
        "a_contribution": 7,
        "a_gain": 15.0,
        "a_total_points_after_round": 211.60000000000002,
        "b_contribution": 8,
        "b_gain": 14.0,
        "b_total_points_after_round": 193.60000000000002,
        "c_contribution": 8,
        "c_gain": 14.0,
        "c_total_points_after_round": 193.60000000000002,
        "d_contribution": 7,
        "d_gain": 15.0,
        "d_total_points_after_round": 209.60000000000002,
        "total_contribution_round": 30
    },
    {
        "round": 15,
        "a_contribution": 7,
        "a_gain": 15.0,
        "a_total_points_after_round": 226.60000000000002,
        "b_contribution": 8,
        "b_gain": 14.0,
        "b_total_points_after_round": 207.60000000000002,
        "c_contribution": 8,
        "c_gain": 14.0,
        "c_total_points_after_round": 207.60000000000002,
        "d_contribution": 7,
        "d_gain": 15.0,
        "d_total_points_after_round": 224.60000000000002,
        "total_contribution_round": 30
    },
    {
        "round": 16,
        "a_contribution": 7,
        "a_gain": 15.0,
        "a_total_points_after_round": 241.60000000000002,
        "b_contribution": 8,
        "b_gain": 14.0,
        "b_total_points_after_round": 221.60000000000002,
        "c_contribution": 8,
        "c_gain": 14.0,
        "c_total_points_after_round": 221.60000000000002,
        "d_contribution": 7,
        "d_gain": 15.0,
        "d_total_points_after_round": 239.60000000000002,
        "total_contribution_round": 30
    },
    {
        "round": 17,
        "a_contribution": 7,
        "a_gain": 15.0,
        "a_total_points_after_round": 256.6,
        "b_contribution": 8,
        "b_gain": 14.0,
        "b_total_points_after_round": 235.60000000000002,
        "c_contribution": 8,
        "c_gain": 14.0,
        "c_total_points_after_round": 235.60000000000002,
        "d_contribution": 7,
        "d_gain": 15.0,
        "d_total_points_after_round": 254.60000000000002,
        "total_contribution_round": 30
    },
    {
        "round": 18,
        "a_contribution": 7,
        "a_gain": 15.0,
        "a_total_points_after_round": 271.6,
        "b_contribution": 8,
        "b_gain": 14.0,
        "b_total_points_after_round": 249.60000000000002,
        "c_contribution": 8,
        "c_gain": 14.0,
        "c_total_points_after_round": 249.60000000000002,
        "d_contribution": 7,
        "d_gain": 15.0,
        "d_total_points_after_round": 269.6,
        "total_contribution_round": 30
    },
    {
        "round": 19,
        "a_contribution": 7,
        "a_gain": 15.0,
        "a_total_points_after_round": 286.6,
        "b_contribution": 8,
        "b_gain": 14.0,
        "b_total_points_after_round": 263.6,
        "c_contribution": 8,
        "c_gain": 14.0,
        "c_total_points_after_round": 263.6,
        "d_contribution": 7,
        "d_gain": 15.0,
        "d_total_points_after_round": 284.6,
        "total_contribution_round": 30
    },
    {
        "round": 20,
        "a_contribution": 7,
        "a_gain": 15.0,
        "a_total_points_after_round": 301.6,
        "b_contribution": 8,
        "b_gain": 14.0,
        "b_total_points_after_round": 277.6,
        "c_contribution": 8,
        "c_gain": 14.0,
        "c_total_points_after_round": 277.6,
        "d_contribution": 7,
        "d_gain": 15.0,
        "d_total_points_after_round": 299.6,
        "total_contribution_round": 30
    }
]