[
    {
        "round": 1,
        "a_contribution": 5,
        "a_gain": 15.4,
        "a_total_points_after_round": 15.4,
        "b_contribution": 8,
        "b_gain": 12.4,
        "b_total_points_after_round": 12.4,
        "total_contribution_round": 13
    },
    {
        "round": 2,
        "a_contribution": 5,
        "a_gain": 15.4,
        "a_total_points_after_round": 30.8,
        "b_contribution": 8,
        "b_gain": 12.4,
        "b_total_points_after_round": 24.8,
        "total_contribution_round": 13
    },
    {
        "round": 3,
        "a_contribution": 5,
        "a_gain": 15.4,
        "a_total_points_after_round": 46.2,
        "b_contribution": 8,
        "b_gain": 12.4,
        "b_total_points_after_round": 37.2,
        "total_contribution_round": 13
    },
    {
        "round": 4,
        "a_contribution": 5,
        "a_gain": 15.4,
        "a_total_points_after_round": 61.6,
        "b_contribution": 8,
        "b_gain": 12.4,
        "b_total_points_after_round": 49.6,
        "total_contribution_round": 13
    },
    {
        "round": 5,
        "a_contribution": 5,
        "a_gain": 15.4,
        "a_total_points_after_round": 77.0,
        "b_contribution": 8,
        "b_gain": 12.4,
        "b_total_points_after_round": 62.0,
        "total_contribution_round": 13
    },
    {
        "round": 6,
        "a_contribution": 5,
        "a_gain": 15.4,
        "a_total_points_after_round": 92.4,
        "b_contribution": 8,
        "b_gain": 12.4,
        "b_total_points_after_round": 74.4,
        "total_contribution_round": 13
    },
    {
        "round": 7,
        "a_contribution": 5,
        "a_gain": 15.4,
        "a_total_points_after_round": 107.80000000000001,
        "b_contribution": 8,
        "b_gain": 12.4,
        "b_total_points_after_round": 86.80000000000001,
        "total_contribution_round": 13
    },
    {
        "round": 8,
        "a_contribution": 5,
        "a_gain": 15.4,
        "a_total_points_after_round": 123.20000000000002,
        "b_contribution": 8,
        "b_gain": 12.4,
        "b_total_points_after_round": 99.20000000000002,
        "total_contribution_round": 13
    },
    {
        "round": 9,
        "a_contribution": 0,
        "a_gain": 16.4,
        "a_total_points_after_round": 139.60000000000002,
        "b_contribution": 8,
        "b_gain": 8.4,
        "b_total_points_after_round": 107.60000000000002,
        "total_contribution_round": 8
    },
    {
        "round": 10,
        "a_contribution": 0,
        "a_gain": 14.0,
        "a_total_points_after_round": 153.60000000000002,
        "b_contribution": 5,
        "b_gain": 9.0,
        "b_total_points_after_round": 116.60000000000002,
        "total_contribution_round": 5
    },
    {
        "round": 11,
        "a_contribution": 0,
        "a_gain": 14.0,
        "a_total_points_after_round": 167.60000000000002,
        "b_contribution": 5,
        "b_gain": 9.0,
        "b_total_points_after_round": 125.60000000000002,
        "total_contribution_round": 5
    },
    {
        "round": 12,
        "a_contribution": 0,
        "a_gain": 14.0,
        "a_total_points_after_round": 181.60000000000002,
        "b_contribution": 5,
        "b_gain": 9.0,
        "b_total_points_after_round": 134.60000000000002,
        "total_contribution_round": 5
    },
    {
        "round": 13,
        "a_contribution": 0,
        "a_gain": 14.0,
        "a_total_points_after_round": 195.60000000000002,
        "b_contribution": 5,
        "b_gain": 9.0,
        "b_total_points_after_round": 143.60000000000002,
        "total_contribution_round": 5
    },
    {
        "round": 14,
        "a_contribution": 0,
        "a_gain": 14.0,
        "a_total_points_after_round": 209.60000000000002,
        "b_contribution": 5,
        "b_gain": 9.0,
        "b_total_points_after_round": 152.60000000000002,
        "total_contribution_round": 5
    },
    {
        "round": 15,
        "a_contribution": 0,
        "a_gain": 14.0,
        "a_total_points_after_round": 223.60000000000002,
        "b_contribution": 5,
        "b_gain": 9.0,
        "b_total_points_after_round": 161.60000000000002,
        "total_contribution_round": 5
    },
    {
        "round": 16,
        "a_contribution": 0,
        "a_gain": 14.0,
        "a_total_points_after_round": 237.60000000000002,
        "b_contribution": 5,
        "b_gain": 9.0,
        "b_total_points_after_round": 170.60000000000002,
        "total_contribution_round": 5
    },
    {
        "round": 17,
        "a_contribution": 0,
        "a_gain": 14.0,
        "a_total_points_after_round": 251.60000000000002,
        "b_contribution": 5,
        "b_gain": 9.0,
        "b_total_points_after_round": 179.60000000000002,
        "total_contribution_round": 5
    },
    {
        "round": 18,
        "a_contribution": 0,
        "a_gain": 14.0,
        "a_total_points_after_round": 265.6,
        "b_contribution": 5,
        "b_gain": 9.0,
        "b_total_points_after_round": 188.60000000000002,
        "total_contribution_round": 5
    },
    {
        "round": 19,
        "a_contribution": 0,
        "a_gain": 14.0,
        "a_total_points_after_round": 279.6,
        "b_contribution": 5,
        "b_gain": 9.0,
        "b_total_points_after_round": 197.60000000000002,
        "total_contribution_round": 5
    },
    {
        "round": 20,
        "a_contribution": 0,
        "a_gain": 14.0,
        "a_total_points_after_round": 293.6,
        "b_contribution": 5,
        "b_gain": 9.0,
        "b_total_points_after_round": 206.60000000000002,
        "total_contribution_round": 5
    }
]