[
    {
        "round": 1,
        "a_contribution": 5,
        "a_gain": 13.0,
        "a_total_points_after_round": 13.0,
        "b_contribution": 5,
        "b_gain": 13.0,
        "b_total_points_after_round": 13.0,
        "c_contribution": 5,
        "c_gain": 13.0,
        "c_total_points_after_round": 13.0,
        "d_contribution": 5,
        "d_gain": 13.0,
        "d_total_points_after_round": 13.0,
        "total_contribution_round": 20
    },
    {
        "round": 2,
        "a_contribution": 4,
        "a_gain": 14.0,
        "a_total_points_after_round": 27.0,
        "b_contribution": 6,
        "b_gain": 12.0,
        "b_total_points_after_round": 25.0,
        "c_contribution": 5,
        "c_gain": 13.0,
        "c_total_points_after_round": 26.0,
        "d_contribution": 5,
        "d_gain": 13.0,
        "d_total_points_after_round": 26.0,
        "total_contribution_round": 20
    },
    {
        "round": 3,
        "a_contribution": 4,
        "a_gain": 12.8,
        "a_total_points_after_round": 39.8,
        "b_contribution": 4,
        "b_gain": 12.8,
        "b_total_points_after_round": 37.8,
        "c_contribution": 5,
        "c_gain": 11.8,
        "c_total_points_after_round": 37.8,
        "d_contribution": 4,
        "d_gain": 12.8,
        "d_total_points_after_round": 38.8,
        "total_contribution_round": 17
    },
    {
        "round": 4,
        "a_contribution": 3,
        "a_gain": 14.600000000000001,
        "a_total_points_after_round": 54.4,
        "b_contribution": 5,
        "b_gain": 12.600000000000001,
        "b_total_points_after_round": 50.4,
        "c_contribution": 6,
        "c_gain": 11.600000000000001,
        "c_total_points_after_round": 49.4,
        "d_contribution": 5,
        "d_gain": 12.600000000000001,
        "d_total_points_after_round": 51.4,
        "total_contribution_round": 19
    },
    {
        "round": 5,
        "a_contribution": 3,
        "a_gain": 14.600000000000001,
        "a_total_points_after_round": 69.0,
        "b_contribution": 6,
        "b_gain": 11.600000000000001,
        "b_total_points_after_round": 62.0,
        "c_contribution": 7,
        "c_gain": 10.600000000000001,
        "c_total_points_after_round": 60.0,
        "d_contribution": 3,
        "d_gain": 14.600000000000001,
        "d_total_points_after_round": 66.0,
        "total_contribution_round": 19
    },
    {
        "round": 6,
        "a_contribution": 3,
        "a_gain": 13.0,
        "a_total_points_after_round": 82.0,
        "b_contribution": 5,
        "b_gain": 11.0,
        "b_total_points_after_round": 73.0,
        "c_contribution": 5,
        "c_gain": 11.0,
        "c_total_points_after_round": 71.0,
        "d_contribution": 2,
        "d_gain": 14.0,
        "d_total_points_after_round": 80.0,
        "total_contribution_round": 15
    },
    {
        "round": 7,
        "a_contribution": 4,
        "a_gain": 12.8,
        "a_total_points_after_round": 94.8,
        "b_contribution": 5,
        "b_gain": 11.8,
        "b_total_points_after_round": 84.8,
        "c_contribution": 4,
        "c_gain": 12.8,
        "c_total_points_after_round": 83.8,
        "d_contribution": 4,
        "d_gain": 12.8,
        "d_total_points_after_round": 92.8,
        "total_contribution_round": 17
    },
    {
        "round": 8,
        "a_contribution": 4,
        "a_gain": 13.600000000000001,
        "a_total_points_after_round": 108.4,
        "b_contribution": 6,
        "b_gain": 11.600000000000001,
        "b_total_points_after_round": 96.4,
        "c_contribution": 5,
        "c_gain": 12.600000000000001,
        "c_total_points_after_round": 96.4,
        "d_contribution": 4,
        "d_gain": 13.600000000000001,
        "d_total_points_after_round": 106.4,
        "total_contribution_round": 19
    },
    {
        "round": 9,
        "a_contribution": 4,
        "a_gain": 14.4,
        "a_total_points_after_round": 122.80000000000001,
        "b_contribution": 7,
        "b_gain": 11.4,
        "b_total_points_after_round": 107.80000000000001,
        "c_contribution": 6,
        "c_gain": 12.4,
        "c_total_points_after_round": 108.80000000000001,
        "d_contribution": 4,
        "d_gain": 14.4,
        "d_total_points_after_round": 120.80000000000001,
        "total_contribution_round": 21
    },
    {
        "round": 10,
        "a_contribution": 5,
        "a_gain": 14.200000000000001,
        "a_total_points_after_round": 137.0,
        "b_contribution": 6,
        "b_gain": 13.200000000000001,
        "b_total_points_after_round": 121.00000000000001,
        "c_contribution": 7,
        "c_gain": 12.200000000000001,
        "c_total_points_after_round": 121.00000000000001,
        "d_contribution": 5,
        "d_gain": 14.200000000000001,
        "d_total_points_after_round": 135.0,
        "total_contribution_round": 23
    },
    {
        "round": 11,
        "a_contribution": 5,
        "a_gain": 14.200000000000001,
        "a_total_points_after_round": 151.2,
        "b_contribution": 7,
        "b_gain": 12.200000000000001,
        "b_total_points_after_round": 133.20000000000002,
        "c_contribution": 6,
        "c_gain": 13.200000000000001,
        "c_total_points_after_round": 134.20000000000002,
        "d_contribution": 5,
        "d_gain": 14.200000000000001,
        "d_total_points_after_round": 149.2,
        "total_contribution_round": 23
    },
    {
        "round": 12,
        "a_contribution": 5,
        "a_gain": 14.200000000000001,
        "a_total_points_after_round": 165.39999999999998,
        "b_contribution": 6,
        "b_gain": 13.200000000000001,
        "b_total_points_after_round": 146.4,
        "c_contribution": 7,
        "c_gain": 12.200000000000001,
        "c_total_points_after_round": 146.4,
        "d_contribution": 5,
        "d_gain": 14.200000000000001,
        "d_total_points_after_round": 163.39999999999998,
        "total_contribution_round": 23
    },
    {
        "round": 13,
        "a_contribution": 5,
        "a_gain": 13.4,
        "a_total_points_after_round": 178.79999999999998,
        "b_contribution": 5,
        "b_gain": 13.4,
        "b_total_points_after_round": 159.8,
        "c_contribution": 6,
        "c_gain": 12.4,
        "c_total_points_after_round": 158.8,
        "d_contribution": 5,
        "d_gain": 13.4,
        "d_total_points_after_round": 176.79999999999998,
        "total_contribution_round": 21
    },
    {
        "round": 14,
        "a_contribution": 5,
        "a_gain": 13.4,
        "a_total_points_after_round": 192.2,
        "b_contribution": 4,
        "b_gain": 14.4,
        "b_total_points_after_round": 174.20000000000002,
        "c_contribution": 7,
        "c_gain": 11.4,
        "c_total_points_after_round": 170.20000000000002,
        "d_contribution": 5,
        "d_gain": 13.4,
        "d_total_points_after_round": 190.2,
        "total_contribution_round": 21
    },
    {
        "round": 15,
        "a_contribution": 5,
        "a_gain": 13.0,
        "a_total_points_after_round": 205.2,
        "b_contribution": 5,
        "b_gain": 13.0,
        "b_total_points_after_round": 187.20000000000002,
        "c_contribution": 5,
        "c_gain": 13.0,
        "c_total_points_after_round": 183.20000000000002,
        "d_contribution": 5,
        "d_gain": 13.0,
        "d_total_points_after_round": 203.2,
        "total_contribution_round": 20
    },
    {
        "round": 16,
        "a_contribution": 5,
        "a_gain": 13.4,
        "a_total_points_after_round": 218.6,
        "b_contribution": 6,
        "b_gain": 12.4,
        "b_total_points_after_round": 199.60000000000002,
        "c_contribution": 5,
        "c_gain": 13.4,
        "c_total_points_after_round": 196.60000000000002,
        "d_contribution": 5,
        "d_gain": 13.4,
        "d_total_points_after_round": 216.6,
        "total_contribution_round": 21
    },
    {
        "round": 17,
        "a_contribution": 5,
        "a_gain": 13.4,
        "a_total_points_after_round": 232.0,
        "b_contribution": 5,
        "b_gain": 13.4,
        "b_total_points_after_round": 213.00000000000003,
        "c_contribution": 6,
        "c_gain": 12.4,
        "c_total_points_after_round": 209.00000000000003,
        "d_contribution": 5,
        "d_gain": 13.4,
        "d_total_points_after_round": 230.0,
        "total_contribution_round": 21
    },
    {
        "round": 18,
        "a_contribution": 5,
        "a_gain": 13.4,
        "a_total_points_after_round": 245.4,
        "b_contribution": 4,
        "b_gain": 14.4,
        "b_total_points_after_round": 227.40000000000003,
        "c_contribution": 7,
        "c_gain": 11.4,
        "c_total_points_after_round": 220.40000000000003,
        "d_contribution": 5,
        "d_gain": 13.4,
        "d_total_points_after_round": 243.4,
        "total_contribution_round": 21
    },
    {
        "round": 19,
        "a_contribution": 5,
        "a_gain": 13.0,
        "a_total_points_after_round": 258.4,
        "b_contribution": 5,
        "b_gain": 13.0,
        "b_total_points_after_round": 240.40000000000003,
        "c_contribution": 5,
        "c_gain": 13.0,
        "c_total_points_after_round": 233.40000000000003,
        "d_contribution": 5,
        "d_gain": 13.0,
        "d_total_points_after_round": 256.4,
        "total_contribution_round": 20
    },
    {
        "round": 20,
        "a_contribution": 5,
        "a_gain": 13.4,
        "a_total_points_after_round": 271.79999999999995,
        "b_contribution": 6,
        "b_gain": 12.4,
        "b_total_points_after_round": 252.80000000000004,
        "c_contribution": 5,
        "c_gain": 13.4,
        "c_total_points_after_round": 246.80000000000004,
        "d_contribution": 5,
        "d_gain": 13.4,
        "d_total_points_after_round": 269.79999999999995,
        "total_contribution_round": 21
    }
]